mistic/__init__.py
mistic/helper_funcs.py
Mistic-0.0.1.dist-info/LICENSE
Mistic-0.0.1.dist-info/METADATA
Mistic-0.0.1.dist-info/WHEEL
Mistic-0.0.1.dist-info/top_level.txt
Mistic-0.0.1.dist-info/RECORD
