Metadata-Version: 2.1
Name: Mistic
Version: 0.0.1
Summary: Mistic: A package for rendering multiple multiplexed images simultaneously
Home-page: https://github.com/MathOnco/Mistic
Author: Sandhya Prabhakaran
Author-email: Sandhya.Prabhakaran@moffitt.org
License: UNKNOWN
Project-URL: Bug Tracker, https://github.com/MathOnco/Mistic/issues
Platform: UNKNOWN
Classifier: Programming Language :: Python :: 3
Classifier: License :: OSI Approved :: MIT License
Classifier: Operating System :: MacOS
Requires-Python: >=3.6
License-File: LICENSE
Requires-Dist: numpy
Requires-Dist: pandas
Requires-Dist: matplotlib
Requires-Dist: scipy
Requires-Dist: scikit-learn
Requires-Dist: PhenoGraph
Requires-Dist: scikit-image
Requires-Dist: seaborn
Requires-Dist: bokeh
Requires-Dist: tifffile
Requires-Dist: Pillow
